{
    "variable_to_simulation": [
        {
            "type": "shape",
            "state": 0,
            "composition": []
        }
    ],
    "parameters": [

    ],
    "functionals": [
        {
            "type": "stress_norm",
            "state": 0
        },
        {
            "type": "collision_barrier",
            "state": 0
        },
        {
            "type": "deformed_collision_barrier",
            "state": 0
        }
    ],
    "solver": {

    },
    "states": [
        {
            "path": "shape-contact-adhesion.json"
        }
    ]
}